math_nk_package/__init__.py
math_nk_package/math_operations.py
math_nk_package-0.1.1.dist-info/METADATA
math_nk_package-0.1.1.dist-info/WHEEL
math_nk_package-0.1.1.dist-info/top_level.txt
math_nk_package-0.1.1.dist-info/RECORD
