Metadata-Version: 2.1
Name: math_nk_package
Version: 0.1.1
Summary: A simple Python package for basic math operations and expression evaluation.
Author: NILESH KISHORE
Author-email: nileshkishore2001@gmail.com
Classifier: Programming Language :: Python :: 3
Classifier: License :: OSI Approved :: MIT License
Classifier: Operating System :: OS Independent
Requires-Python: >=3.6
